prgb_pkg/__init__.py
prgb_pkg/decorators.py
prgb_pkg/prgb.py
prgb_pkg/prgb_iter.py
prgb_pkg/prgb_window.py
prgb_pkg-0.2.2.dist-info/LICENSE
prgb_pkg-0.2.2.dist-info/METADATA
prgb_pkg-0.2.2.dist-info/WHEEL
prgb_pkg-0.2.2.dist-info/top_level.txt
prgb_pkg-0.2.2.dist-info/RECORD
