Metadata-Version: 2.1
Name: prgb-pkg
Version: 0.2.2
Summary: Windowed progress bars for loop progress tracking, like in tqdm.
Home-page: UNKNOWN
Author: Piotr Bernaskiewicz
Author-email: mojczat0@gmail.com
Maintainer: KodenejmBerni
License: UNKNOWN
Project-URL: Source Code, https://github.com/KodenejmBerni/prgb_pkg
Platform: UNKNOWN
Classifier: Programming Language :: Python :: 3
Classifier: Operating System :: Microsoft :: Windows
Classifier: License :: OSI Approved :: GNU General Public License v3 (GPLv3)
Classifier: Intended Audience :: Developers
Classifier: Development Status :: 4 - Beta
Classifier: Topic :: Software Development
Requires-Python: >=3.7
